{
	"locale": "ca-ES",
	"value": {
		"Role_Category": "Categoria",
		"Role_Values": "Valors",
		"Role_Image": "Imatge",
		"Visual_General": "General",
		"Visual_Orientation": "Orientació",
		"Visual_Orientation_Vertical": "Vertical",
		"Visual_Orientation_Horizontal": "Horitzontal",
		"Visual_Columns": "Columnes",
		"Visual_Rows": "Files",
		"Visual_ShowDisabled": "Show Disabled",
		"Visual_ShowDisabled_Inplace": "Inplace",
		"Visual_ShowDisabled_Bottom": "Part inferior",
		"Visual_ShowDisabled_Hide": "Amaga",
		"Visual_MultipleSelection": "Multiple selection",
		"Visual_ForcedSelection": "Forced selection",
		"Visual_Header": "Capçalera",
		"Visual_Title": "Títol",
		"Visual_FontColor": "Color de la lletra",
		"Visual_Background": "Fons",
		"Visual_TextSize": "Mida del text",
		"Visual_OutlineColor": "Outline Color",
		"Visual_OutlineWeight": "Outline Weight",
		"Visual_Chiclets": "Chiclets",
		"Visual_Height": "Alçada",
		"Visual_Width": "Amplada",
		"Visual_Transparancy": "Transparència",
		"Visual_SelectedColor": "Selected Color",
		"Visual_HoverColor": "Color en apuntar",
		"Visual_UnselectedColor": "Unselected Color",
		"Visual_DisabledColor": "Color inhabilitat",
		"Visual_TextColor": "Color del text",
		"Visual_Padding": "Espaiat",
		"Visual_OutlineStyle": "Outline Style",
		"Visual_OutlineStyle_Rounded": "Rounded",
		"Visual_OutlineStyle_Cut": "Retalla",
		"Visual_OutlineStyle_Square": "Quadrat",
		"Visual_Images": "Imatges",
		"Visual_Images_Split": "Image Split",
		"Visual_Images_Stretch": "Stretch image",
		"Visual_Images_Bottom": "Bottom image"
	}
}